README.md
onebrain-client
setup.py
casbrain_client.egg-info/PKG-INFO
casbrain_client.egg-info/SOURCES.txt
casbrain_client.egg-info/dependency_links.txt
casbrain_client.egg-info/requires.txt
casbrain_client.egg-info/top_level.txt
onebrain/__init__.py
onebrain/dataset.py
onebrain/mnist.py
onebrain/onebrain.py
onebrain/task.py
onebrain/utils/FileUpload.py
onebrain/utils/__init__.py
onebrain/utils/config.py
onebrain/utils/configtool.py
onebrain/utils/process.py
onebrain/utils/requeststool.py
onebrain/utils/rsatool.py
onebrain/utils/yamltool.py