Metadata-Version: 1.1
Name: casbrain-client
Version: 0.0.52
Summary: casbrain客户端
Home-page: UNKNOWN
Author: KeLi
Author-email: UNKNOWN
License: UNKNOWN
Platform: UNKNOWN
Classifier: Programming Language :: Python :: 3
Classifier: License :: OSI Approved :: MIT License
Classifier: Operating System :: OS Independent
